dff.v
module dff(
    input clk,
    input reset,
    input d,
    input seed,          // <-- new input for seeding
    output reg q
);
    always @(posedge clk or posedge reset) begin
        if (reset)
            q <= seed;   // initialize from seed
        else
            q <= d;
    end
endmodule

xor2.v
module xor2(
    input a,
    input b,
    output y
);
    assign y = a ^ b;
endmodule

lfsr.v
`timescale 1ns/1ps
module lfsr(
    input clk,
    input reset,
    output [7:0] random
);
    wire [7:0] q;
    wire feedback;
    wire xor1, xor2_out, xor3_out;

    // XOR feedback taps (bits 7,5,4,3)
    xor2 x1(.a(q[7]), .b(q[5]), .y(xor1));
    xor2 x2(.a(xor1), .b(q[4]), .y(xor2_out));
    xor2 x3(.a(xor2_out), .b(q[3]), .y(feedback));

    // Seed bits for initial non-zero value
    wire [7:0] seed = 8'b10101010;

    // D flip-flops with seed inputs
    dff f0(.clk(clk), .reset(reset), .d(feedback), .seed(seed[0]), .q(q[0]));
    dff f1(.clk(clk), .reset(reset), .d(q[0]), .seed(seed[1]), .q(q[1]));
    dff f2(.clk(clk), .reset(reset), .d(q[1]), .seed(seed[2]), .q(q[2]));
    dff f3(.clk(clk), .reset(reset), .d(q[2]), .seed(seed[3]), .q(q[3]));
    dff f4(.clk(clk), .reset(reset), .d(q[3]), .seed(seed[4]), .q(q[4]));
    dff f5(.clk(clk), .reset(reset), .d(q[4]), .seed(seed[5]), .q(q[5]));
    dff f6(.clk(clk), .reset(reset), .d(q[5]), .seed(seed[6]), .q(q[6]));
    dff f7(.clk(clk), .reset(reset), .d(q[6]), .seed(seed[7]), .q(q[7]));

    assign random = q;
endmodule

tb_lfsr.v
`timescale 1ns/1ps
module tb_lfsr;
    reg clk = 0;
    reg reset;
    wire [7:0] random;

    lfsr uut (
        .clk(clk),
        .reset(reset),
        .random(random)
    );

    always #5 clk = ~clk;

    initial begin
        $dumpfile("wave.vcd");
        $dumpvars(0, tb_lfsr);

        reset = 1; #10;
        reset = 0; // release reset

        repeat (30) begin
            #10;
            $display("Random: %b (%0d)", random, random);
        end

        $finish;
    end
endmodule

wave.vcd
$date
	Wed Oct 29 21:48:51 2025
$end
$version
	Icarus Verilog
$end
$timescale
	1ps
$end
$scope module tb_lfsr $end
$var wire 8 ! random [7:0] $end
$var reg 1 " clk $end
$var reg 1 # reset $end
$scope module uut $end
$var wire 1 " clk $end
$var wire 8 $ random [7:0] $end
$var wire 1 # reset $end
$var wire 8 % seed [7:0] $end
$var wire 1 & xor2_out $end
$var wire 1 ' xor1 $end
$var wire 8 ( q [7:0] $end
$var wire 1 ) feedback $end
$scope module f0 $end
$var wire 1 " clk $end
$var wire 1 # reset $end
$var wire 1 * seed $end
$var wire 1 ) d $end
$var reg 1 + q $end
$upscope $end
$scope module f1 $end
$var wire 1 " clk $end
$var wire 1 , d $end
$var wire 1 # reset $end
$var wire 1 - seed $end
$var reg 1 . q $end
$upscope $end
$scope module f2 $end
$var wire 1 " clk $end
$var wire 1 / d $end
$var wire 1 # reset $end
$var wire 1 0 seed $end
$var reg 1 1 q $end
$upscope $end
$scope module f3 $end
$var wire 1 " clk $end
$var wire 1 2 d $end
$var wire 1 # reset $end
$var wire 1 3 seed $end
$var reg 1 4 q $end
$upscope $end
$scope module f4 $end
$var wire 1 " clk $end
$var wire 1 5 d $end
$var wire 1 # reset $end
$var wire 1 6 seed $end
$var reg 1 7 q $end
$upscope $end
$scope module f5 $end
$var wire 1 " clk $end
$var wire 1 8 d $end
$var wire 1 # reset $end
$var wire 1 9 seed $end
$var reg 1 : q $end
$upscope $end
$scope module f6 $end
$var wire 1 " clk $end
$var wire 1 ; d $end
$var wire 1 # reset $end
$var wire 1 < seed $end
$var reg 1 = q $end
$upscope $end
$scope module f7 $end
$var wire 1 " clk $end
$var wire 1 > d $end
$var wire 1 # reset $end
$var wire 1 ? seed $end
$var reg 1 @ q $end
$upscope $end
$scope module x1 $end
$var wire 1 A a $end
$var wire 1 B b $end
$var wire 1 ' y $end
$upscope $end
$scope module x2 $end
$var wire 1 ' a $end
$var wire 1 C b $end
$var wire 1 & y $end
$upscope $end
$scope module x3 $end
$var wire 1 & a $end
$var wire 1 D b $end
$var wire 1 ) y $end
$upscope $end
$upscope $end
$upscope $end
$enddefinitions $end
$comment Show the parameter values. $end
$dumpall
$end
#0
$dumpvars
1D
0C
1B
1A
1@
1?
0>
0=
0<
1;
1:
19
08
07
06
15
14
13
02
01
00
1/
1.
1-
0,
0+
0*
1)
b10101010 (
0'
0&
b10101010 %
b10101010 $
1#
0"
b10101010 !
$end
#5000
1"
#10000
0"
0#
#15000
1&
1,
0/
12
05
0D
18
1C
0;
0B
1>
0A
1+
0.
11
04
17
0:
1=
b1010101 !
b1010101 $
b1010101 (
0@
1"
#20000
0"
#25000
0&
1)
1A
0>
1;
1B
08
0C
15
1D
02
1/
1@
0=
1:
07
14
01
b10101011 !
b10101011 $
b10101011 (
1.
1"
#30000
0"
#35000
1&
12
05
0D
18
1C
0;
0B
1>
0A
11
04
17
0:
1=
b1010111 !
b1010111 $
b1010111 (
0@
1"
#40000
0"
#45000
0&
1)
1A
0>
1;
1B
08
0C
15
1D
1@
0=
1:
07
b10101111 !
b10101111 $
b10101111 (
14
1"
#50000
0"
#55000
0)
1&
18
1C
0;
0B
1>
0A
17
0:
1=
b1011111 !
b1011111 $
b1011111 (
0@
1"
#60000
0"
#65000
1A
0>
1;
1B
0,
1@
0=
1:
b10111110 !
b10111110 $
b10111110 (
0+
1"
#70000
0"
#75000
1)
0&
1'
0/
1>
0A
0.
1=
b1111100 !
b1111100 $
b1111100 (
0@
1"
#80000
0"
#85000
0)
1&
0'
1A
02
1,
1@
01
b11111001 !
b11111001 $
b11111001 (
1+
1"
#90000
0"
#95000
1)
0,
1/
05
0D
0+
1.
b11110010 !
b11110010 $
b11110010 (
04
1"
#100000
0"
#105000
0)
0&
08
0C
12
0/
1,
07
11
0.
b11100101 !
b11100101 $
b11100101 (
1+
1"
#110000
0"
#115000
1&
0)
1'
0,
1/
02
15
1D
0;
0B
0+
1.
01
14
b11001010 !
b11001010 $
b11001010 (
0:
1"
#120000
0"
#125000
0&
0)
0>
18
1C
05
0D
12
0/
0=
17
04
11
b10010100 !
b10010100 $
b10010100 (
0.
1"
#130000
0"
#135000
1&
02
15
1D
08
0C
1;
1B
0A
01
14
07
1:
b101000 !
b101000 $
b101000 (
0@
1"
#140000
0"
#145000
0'
1&
1)
1>
0;
0B
18
1C
05
0D
1=
0:
17
b1010000 !
b1010000 $
b1010000 (
04
1"
#150000
0"
#155000
0)
0&
1,
08
0C
1;
1B
0>
1A
1+
07
1:
0=
b10100001 !
b10100001 $
b10100001 (
1@
1"
#160000
0"
#165000
0A
1>
0;
0B
1/
0,
0@
1=
0:
1.
b1000010 !
b1000010 $
b1000010 (
0+
1"
#170000
0"
#175000
1)
1&
1'
0/
12
0>
1A
0.
11
0=
b10000100 !
b10000100 $
b10000100 (
1@
1"
#180000
0"
#185000
0&
0'
1)
0A
15
1D
02
1,
0@
14
01
b1001 !
b1001 $
b1001 (
1+
1"
#190000
0"
#195000
1&
1/
05
0D
18
1C
1.
04
b10011 !
b10011 $
b10011 (
17
1"
#200000
0"
#205000
1)
1'
1&
1;
1B
08
0C
12
1:
07
b100111 !
b100111 $
b100111 (
11
1"
#210000
0"
#215000
0&
1)
0'
15
1D
0;
0B
1>
14
0:
b1001111 !
b1001111 $
b1001111 (
1=
1"
#220000
0"
#225000
1)
1'
0&
1A
0>
18
1C
1@
0=
b10011111 !
b10011111 $
b10011111 (
17
1"
#230000
0"
#235000
1;
1B
0A
1:
b111111 !
b111111 $
b111111 (
0@
1"
#240000
0"
#245000
1>
b1111111 !
b1111111 $
b1111111 (
1=
1"
#250000
0"
#255000
0)
1&
0'
1A
b11111111 !
b11111111 $
b11111111 (
1@
1"
#260000
0"
#265000
0,
b11111110 !
b11111110 $
b11111110 (
0+
1"
#270000
0"
#275000
0/
b11111100 !
b11111100 $
b11111100 (
0.
1"
#280000
0"
#285000
02
b11111000 !
b11111000 $
b11111000 (
01
1"
#290000
0"
#295000
1)
05
0D
b11110000 !
b11110000 $
b11110000 (
04
1"
#300000
0"
#305000
0)
0&
08
0C
1,
07
b11100001 !
b11100001 $
b11100001 (
1+
1"
